ProcessWatcher/__init__.py
ProcessWatcher/process_watcher.py
ProcessWatcher/communicate/__init__.py
ProcessWatcher/communicate/dbus_notify.py
ProcessWatcher/communicate/email.py
ProcessWatcher/process/__init__.py
proc_watcher-0.2.2.data/data/etc/process-watcher/watcher.conf
proc_watcher-0.2.2.dist-info/DESCRIPTION.rst
proc_watcher-0.2.2.dist-info/METADATA
proc_watcher-0.2.2.dist-info/RECORD
proc_watcher-0.2.2.dist-info/WHEEL
proc_watcher-0.2.2.dist-info/entry_points.txt
proc_watcher-0.2.2.dist-info/metadata.json
proc_watcher-0.2.2.dist-info/top_level.txt
